mcpm/__init__.py
mcpm/cli.py
mcpm/global_config.py
mcpm/version.py
mcpm/clients/__init__.py
mcpm/clients/base.py
mcpm/clients/client_config.py
mcpm/clients/client_registry.py
mcpm/clients/managers/__init__.py
mcpm/clients/managers/claude_code.py
mcpm/clients/managers/claude_desktop.py
mcpm/clients/managers/cline.py
mcpm/clients/managers/codex_cli.py
mcpm/clients/managers/continue_extension.py
mcpm/clients/managers/cursor.py
mcpm/clients/managers/fiveire.py
mcpm/clients/managers/gemini_cli.py
mcpm/clients/managers/goose.py
mcpm/clients/managers/qwen_cli.py
mcpm/clients/managers/trae.py
mcpm/clients/managers/vscode.py
mcpm/clients/managers/windsurf.py
mcpm/commands/__init__.py
mcpm/commands/client.py
mcpm/commands/config.py
mcpm/commands/doctor.py
mcpm/commands/edit.py
mcpm/commands/info.py
mcpm/commands/inspect.py
mcpm/commands/install.py
mcpm/commands/list.py
mcpm/commands/migrate.py
mcpm/commands/new.py
mcpm/commands/profile.py
mcpm/commands/run.py
mcpm/commands/search.py
mcpm/commands/share.py
mcpm/commands/uninstall.py
mcpm/commands/usage.py
mcpm/commands/profile/__init__.py
mcpm/commands/profile/create.py
mcpm/commands/profile/edit.py
mcpm/commands/profile/inspect.py
mcpm/commands/profile/interactive.py
mcpm/commands/profile/list.py
mcpm/commands/profile/remove.py
mcpm/commands/profile/run.py
mcpm/commands/profile/share.py
mcpm/core/schema.py
mcpm/core/tunnel.py
mcpm/core/utils/log_manager.py
mcpm/fastmcp_integration/__init__.py
mcpm/fastmcp_integration/config.py
mcpm/fastmcp_integration/middleware.py
mcpm/fastmcp_integration/proxy.py
mcpm/migration/__init__.py
mcpm/migration/v1_detector.py
mcpm/migration/v1_migrator.py
mcpm/monitor/__init__.py
mcpm/monitor/base.py
mcpm/monitor/event.py
mcpm/monitor/sqlite.py
mcpm/profile/profile_config.py
mcpm/schemas/full_server_config.py
mcpm/utils/__init__.py
mcpm/utils/config.py
mcpm/utils/display.py
mcpm/utils/logging_config.py
mcpm/utils/non_interactive.py
mcpm/utils/platform.py
mcpm/utils/repository.py
mcpm-2.13.0.dist-info/METADATA
mcpm-2.13.0.dist-info/WHEEL
mcpm-2.13.0.dist-info/entry_points.txt
mcpm-2.13.0.dist-info/licenses/LICENSE
mcpm-2.13.0.dist-info/RECORD
