Metadata-Version: 2.4
Name: mcpm
Version: 2.13.0
Summary: MCPM - Model Context Protocol Manager
Project-URL: Homepage, https://mcpm.sh
Project-URL: Repository, https://github.com/pathintegral-institute/mcpm.sh
Project-URL: Issues, https://github.com/pathintegral-institute/mcpm.sh/issues
Author: MCPM Contributors
Maintainer: Path Integral Institute
License-Expression: MIT
License-File: LICENSE
Keywords: Claude Desktop,Cursor,MCP,MCPM,Model Context Protocol,Windsurf
Requires-Python: >=3.11
Requires-Dist: click>=8.1.3
Requires-Dist: deprecated>=1.2.18
Requires-Dist: duckdb>=1.2.2
Requires-Dist: fastmcp==2.13.0
Requires-Dist: inquirerpy>=0.3.4
Requires-Dist: jsonschema>=4.24.0
Requires-Dist: mcp>=1.8.0
Requires-Dist: prompt-toolkit>=3.0.0
Requires-Dist: psutil>=7.0.0
Requires-Dist: pydantic<2.12.0,>=2.5.1
Requires-Dist: requests>=2.28.0
Requires-Dist: rich-click>=1.8.0
Requires-Dist: rich-gradient>=0.3.2
Requires-Dist: rich>=12.0.0
Requires-Dist: ruamel-yaml>=0.18.10
Requires-Dist: tomli-w>=1.2.0
Requires-Dist: tomli>=2.2.1
Requires-Dist: watchfiles>=1.0.4
